{
    "ecclesiarcy": {"name": "Ecclesiarcy", "kill_team": "adepta_sororitas"},
    "novitiate": {"name": "Novitiate", "kill_team": "adepta_sororitas"},
    "exactionsquad": {"name": "Exaction Squad", "kill_team": "adeptus_arbites"},
    "talons": {"name": "Talons of the Emperor", "kill_team": "adeptus_custodes"},
    "hunterclade": {"name": "Hunter Clade", "kill_team": "adeptus_mechanicus"},
    "starstrider": {"name": "Elucidian Starstrider", "kill_team": "astra_cartographica"},
    "imperialguard": {"name": "Imperial Guard", "kill_team": "astra_militarum"},
    "karskin": {"name": "Karskin", "kill_team": "astra_militarum"},
    "veteranguard": {"name": "Veteran Guardsman", "kill_team": "astra_militarum"},
    "breachers": {"name": "Imperial Navy Breacher", "kill_team": "navis_imperialis"},
    "intercession": {"name": "Intercession Squad", "kill_team": "space_marines"},
    "phobosstrike": {"name": "Phobos Strike Team", "kill_team": "space_marines"},
    "spacemarines": {"name": "Space Marines", "kill_team": "space_marines"},
    "chaosdaemons": {"name": "Chaos Daemons", "kill_team": "chaos_daemons"},
    "gellerpox": {"name": "Gellerpox Infected", "kill_team": "chaos_daemons"},
    "blooded": {"name": "Blooded", "kill_team": "chaos_space_marines"},
    "legionary": {"name": "Legionary", "kill_team": "chaos_space_marines"},
    "traitors": {"name": "Traitor Space Marines", "kill_team": "chaos_space_marines"},
    "deathguard": {"name": "Death Guard", "kill_team": "death_guard"},
    "warpcoven": {"name": "Warpcoven", "kill_team": "thousand_sons"},
    "corsairs": {"name": "Corsair Voidscarred", "kill_team": "corsairs"},
    "craftworld": {"name": "Craftworld", "kill_team": "craftworld"},
    "commorrite": {"name": "Commorrite", "kill_team": "drukhari"},
    "archon": {"name": "Hand of Archon", "kill_team": "drukhari"},
    "troupe": {"name": "Void-dancer Troupe", "kill_team": "harlequins"},
    "brood": {"name": "Brood Coven", "kill_team": "genestealer_cults"},
    "wyrmblade": {"name": "Wyrmblade", "kill_team": "genestealer_cults"},
    "farstalker_kindband": {"name": "Farstalker Kindband", "kill_team": "kroot"},
    "hierotek": {"name": "Hierotek Circle", "kill_team": "necrons"},
    "tomb": {"name": "Tomb World", "kill_team": "necrons"},
    "greenskin": {"name": "Greenskin", "kill_team": "orks"},
    "kommando": {"name": "Kommando", "kill_team": "orks"},
    "cadre_mercenary": {"name": "Cadre Mercenary", "kill_team": "tau_empire"},
    "hunter_cadre": {"name": "Hunter Cadre", "kill_team": "tau_empire"},
    "pathfinder": {"name": "Pathfinder", "kill_team": "tau_empire"},
    "hivefleet": {"name": "Hive Fleet", "kill_team": "tyranids"}
}
